sapphire.py-0.2.3.data/data/sapphirepy_bin/sapphirewrapper-amd64.dll
sapphire.py-0.2.3.data/data/sapphirepy_bin/sapphirewrapper-amd64.dylib
sapphire.py-0.2.3.data/data/sapphirepy_bin/sapphirewrapper-amd64.so
sapphire.py-0.2.3.data/data/sapphirepy_bin/sapphirewrapper-arm64.dylib
sapphire.py-0.2.3.data/data/sapphirepy_bin/sapphirewrapper-arm64.so
sapphirepy/__init__.py
sapphirepy/wrapper.py
sapphire.py-0.2.3.dist-info/LICENSE
sapphire.py-0.2.3.dist-info/METADATA
sapphire.py-0.2.3.dist-info/WHEEL
sapphire.py-0.2.3.dist-info/top_level.txt
sapphire.py-0.2.3.dist-info/RECORD
